_formatparse/__init__.py
_formatparse/_formatparse.cpython-313-darwin.so
formatparse/__init__.py
formatparse/py.typed
formatparse-0.6.1.dist-info/METADATA
formatparse-0.6.1.dist-info/WHEEL
formatparse-0.6.1.dist-info/licenses/LICENSE
formatparse-0.6.1.dist-info/RECORD
