Metadata-Version: 2.4
Name: formatparse
Version: 0.6.1
Classifier: Programming Language :: Rust
Classifier: Programming Language :: Python :: Implementation :: CPython
Classifier: Programming Language :: Python :: Implementation :: PyPy
Classifier: Typing :: Typed
Requires-Dist: mutmut>=2.0 ; extra == 'dev'
Requires-Dist: hypothesis>=6.0 ; extra == 'test'
Requires-Dist: pytest-cov>=4.0 ; extra == 'test'
Requires-Dist: pytest-benchmark>=4.0 ; extra == 'test'
Requires-Dist: pympler>=0.9 ; extra == 'test'
Requires-Dist: memory-profiler>=0.60 ; extra == 'test'
Provides-Extra: dev
Provides-Extra: test
License-File: LICENSE
Summary: Parse strings using a specification based on the Python format() syntax (Rust implementation)
Keywords: parse,format,string,parsing
Author-email: Odos Matthews <odosmatthews@gmail.com>
License: MIT
Requires-Python: >=3.8
Project-URL: Homepage, https://github.com/eddiethedean/formatparse
Project-URL: Repository, https://github.com/eddiethedean/formatparse
